{
  "name": "Kyle Holland",
  "age": 45,
  "address": {
    "street": "Gita Boulevard",
    "city": "Majiluc",
    "state": "TN",
    "zip": "84846"
  },
  "contact": {
    "phone": "(627) 815-4760",
    "servicePhone": "800593637"
  },
  "birthday": "1981-01-12T06:13:24.242Z",
  "ip": "38.229.27.85",
  "foo": "bar",
  "profile": {
    "about": "Higohli va kukece leagiza mo hi mebves reg ahic somuwu duwe varad tipwogcuw ojalimlol webumobi bu ed kemla. Tuzo esefo panof kurzefac feladac sihig bahcu gisipu formul lukubim nuvetwud dovifi po migu elo osgic tic now. Us copijav rewge bengame mapapib ze ta vesovvu bizvujod di cogwit feheh damle zuvakic. Gozucfu uh nol hi rocese go bube gokuku hobwen vemen lioloju hume saagi siw.",
    "bio": "Kucaz lidme najam kowcug ra mu kivmobe zi kakocobu foh sawu tucida. Zeg jodez me sag ni bakuwa goc rekizdo hareh sive egvi cahka se. Ikkoci eweze topijo ga remvasub ga tiwhefcu amoboeka ansareb zuh rupapehos momo binuco cuzole rig nir. Loubo zuf ad tarle nefin ruba rober zid hol zucfef oswem vidudte so."
  },
  "apiKey": "47020146313e645826b659d06197fb99de8a0cb211e5e576f5910fd1a3adea9e",
  "currency": {
    "code": "HKD",
    "name": "Hong Kong Dollar"
  }
}