{
  "name": "Tony Lyons",
  "age": 52,
  "address": {
    "street": "Wumwa Avenue",
    "city": "Hawnoih",
    "state": "WI",
    "zip": "92750"
  },
  "contact": {
    "phone": "(854) 916-8438",
    "servicePhone": "800917562"
  },
  "birthday": "1961-09-18T23:30:38.011Z",
  "ip": "75.245.78.115",
  "foo": "bar",
  "profile": {
    "about": "Ralefuv fampug omi birhedzig lu idefe ropi tokifeof raba sinaco nutleshiw naba ipove ulalike ugenog serozjew. Goof baz zid edieleara piga vewe gi anaonov ceev falotij pa cicel ges mukeje di lelopes kano. Alefu avife nufezfa zuvvoh no pephinit sinohem etufu jukamaneb sihan fi rugahe gohukomu bokorut. Jefjus hob lu gulo oguipu da namowid kijamge kud fed haitfa zeimdi.",
    "bio": "Jeklage haszu geg akotetdoj bid saushu oga erizuztew vunotgid gipmuw ducuc ejuugujo so. Deve hegesus ja urivaprev nivuz fewtajma og cehonal zafoc bepihnaz ifebuku dusumiv wero koju iclofeh mu hoc ralu. Asaimihu coca harkajbo oklogod li rasromas uctelje cozki mihvuw henot fe fagwizol. Bo wausef ifos ipuna ovo jopupe jebetgup morwivhac we por sib naw."
  },
  "apiKey": "edd40d6c258c5836b4a517a2af276b9a281dce80d3dff9c3fb27b2e98e653d79",
  "currency": {
    "code": "GTQ",
    "name": "Guatemala Quetzal"
  }
}