{
  "name": "William Stokes",
  "age": 33,
  "address": {
    "street": "Veek Place",
    "city": "Avbetbo",
    "state": "NC",
    "zip": "42271"
  },
  "contact": {
    "phone": "(542) 771-2351",
    "servicePhone": "800878384"
  },
  "birthday": "1981-10-09T13:47:27.611Z",
  "ip": "5.241.161.194",
  "foo": "bar",
  "profile": {
    "about": "Valfaf ebeejic jil wof wucodajo padakev juzvi vajdascut huftav favpihpe humgitge ifo. Olfevog makpaja dukaddo tawwo koc det suhlewo jah il julmuvu lub afo jog paros. Iwa heconoze osi rinvewsor apaijvol jigsil mujo nuvu weefiho makkic rogvuf suhozinu wivimi ugi ej dirhopbi ufa sohzo. Imbo duhjoevo ojdulza memzepij zezad ut sufwedu wazeha uraatuzuf ezaahfi atimuf tulut. Re fotri sonregig wore nepcesoj ketiheci ahiah wuw relajugog vesfu ziwsa ro femhan ura kopifeki wojirac ene.",
    "bio": "Tiphitgo nik muf jo usa mi vi isiojga tib ke nosca vafeh evepur lefvono bi pawuze. Hewol biwowez fukkuha roccuvek gok avu so ugbalil cuc jem rigi firbile. Pu wigkoz zi jet ogciuc somso du jeneguf tiwab lelmid za gow. Gutpis uwoiho ugageula labapi rigiz nuj sogpa hi cijbid wiw huwijeic ga gumek tafoozo. Jirpictu miz viz ega ka esmoemi pel de zu nobut sajewi wioko rav la rusulce lalcuojo uko ce. Esejjad uhwanila zoevci fotzuak age bumgudak kouc azeme lozamo rol uhe pizaru utite rifju wauje. Bafgim mivruab aseguwun tiohe cuza saib jal heidoli torzuvo ur hordeju mimu pakobe."
  },
  "apiKey": "cd53a04f2a8fece4e6971436c04d348f3f9a870cb8fff137404982701b172ce7",
  "currency": {
    "code": "CLP",
    "name": "Chile Peso"
  }
}